{"inkVersion":20,"root":[["^Hello! Welcome to the Orchard! ",{"->":"Choices"},"\n",["done",{"#f":5,"#n":"g-0"}],null],"done",{"Choices":[["ev","str","^Are you a nudist?","/str","/ev",{"*":".^.c-0","flg":20},"ev","str","^What kind of fruit grows here?","/str","/ev",{"*":".^.c-1","flg":20},"ev","str","^Can I touch your fruits?","/str","/ev",{"*":".^.c-2","flg":20},{"c-0":["^ ",{"->":"Nudist"},"\n",{"#f":5}],"c-1":["^ ",{"->":"Apples"},"\n",{"#f":5}],"c-2":["^ ",{"->":"Slap"},"\n",{"#f":5}]}],{"#f":1}],"Slap":["^(SALLY SLAPPED YOU!)","\n","end",{"#f":1}],"Apples":[["^This is an Apple orchard!","\n","ev","str","^Thanks!","/str","/ev",{"*":".^.c-0","flg":20},"ev","str","^Is that your favorite fruit?","/str","/ev",{"*":".^.c-1","flg":20},{"c-0":["^ ",{"->":"welcome"},"\n",{"#f":5}],"c-1":["^ ",{"->":"favorite"},"\n",{"#f":5}]}],{"#f":1}],"favorite":["^Um, that's none of your business, okay?","\n",{"->":"Choices"},{"#f":1}],"welcome":["^Oh, you're welcome :)","\n","end",{"#f":1}],"Nudist":["^Ew, no!","\n",{"->":"Choices"},{"#f":1}],"#f":1}],"listDefs":{}}